Metadata-Version: 2.1
Name: scoping
Version: 0.1.2
Summary: Probably the best way to simulate block scopes in Python.
Home-page: https://github.com/l74d/scoping
Author: l74d
Author-email: l.d.code@outlook.com
License: UNKNOWN
Project-URL: Bug Tracker, https://github.com/l74d/scoping/issues
Platform: UNKNOWN
Classifier: Programming Language :: Python :: 3
Classifier: License :: OSI Approved :: BSD License
Classifier: Operating System :: OS Independent
Requires-Python: >=3.6
